setup.py
dummy_envipy_dependency/__init__.py
dummy_envipy_dependency.egg-info/PKG-INFO
dummy_envipy_dependency.egg-info/SOURCES.txt
dummy_envipy_dependency.egg-info/dependency_links.txt
dummy_envipy_dependency.egg-info/top_level.txt