Metadata-Version: 1.0
Name: dummy-envipy-dependency
Version: 0.0.2
Summary: we need this package to test envipy updates
Home-page: UNKNOWN
Author: Uwe Schmitt
Author-email: uwe.schmitt@id.ethz.ch
License: BSD
Platform: UNKNOWN
